pytest_jest/__init__.py
pytest_jest/plugin.py
pytest_jest-0.3.0.dist-info/METADATA
pytest_jest-0.3.0.dist-info/RECORD
pytest_jest-0.3.0.dist-info/WHEEL
pytest_jest-0.3.0.dist-info/entry_points.txt
pytest_jest-0.3.0.dist-info/top_level.txt
